mpesa_stk/__init__.py
mpesa_stk/stk.py
mpesa_stk-0.1.0.dist-info/METADATA
mpesa_stk-0.1.0.dist-info/WHEEL
mpesa_stk-0.1.0.dist-info/top_level.txt
mpesa_stk-0.1.0.dist-info/RECORD
