Metadata-Version: 2.4
Name: mpesa-stk
Version: 0.1.0
Summary: A simple Python library for Safaricom M-Pesa STK Push integration
Home-page: https://github.com/BrianZiro/mpesa_stk_library.git
Author: Brian Ziro
Author-email: brianziro44@gmail.com
Classifier: Programming Language :: Python :: 3
Classifier: License :: OSI Approved :: MIT License
Classifier: Operating System :: OS Independent
Requires-Python: >=3.6
Requires-Dist: requests>=2.20.0
Dynamic: author
Dynamic: author-email
Dynamic: classifier
Dynamic: home-page
Dynamic: requires-dist
Dynamic: requires-python
Dynamic: summary
